{
  "accuracy": 0.6,
  "total_cases": 200,
  "correct_cases": 120,
  "incorrect_cases": 80,
  "category_counts": {
    "SYNTAX_ERROR": 40,
    "MISC_ERROR": 2,
    "WRONG_VALUE": 2,
    "RELEVANT_BUT_INCORRECT": 8,
    "EXACTLY_SAME_MEANING": 7,
    "LANGUAGE_MISMATCH_WRONG_VALUE": 0,
    "LANGUAGE_MISMATCH_RELEVANT_BUT_INCORRECT": 2,
    "LANGUAGE_MISMATCH_EXACTLY_SAME_MEANING": 19,
    "OTHER_ERROR": 0
  },
  "category_samples": {
    "SYNTAX_ERROR": [
      "multiple_10",
      "multiple_20",
      "multiple_27",
      "multiple_40",
      "multiple_53",
      "multiple_67",
      "multiple_68",
      "multiple_80",
      "multiple_86",
      "multiple_87",
      "multiple_92",
      "multiple_103",
      "multiple_109",
      "multiple_110",
      "multiple_120",
      "multiple_123",
      "multiple_134",
      "multiple_135",
      "multiple_138",
      "multiple_139",
      "multiple_140",
      "multiple_142",
      "multiple_147",
      "multiple_152",
      "multiple_156",
      "multiple_161",
      "multiple_162",
      "multiple_164",
      "multiple_165",
      "multiple_168",
      "multiple_169",
      "multiple_171",
      "multiple_173",
      "multiple_179",
      "multiple_183",
      "multiple_184",
      "multiple_187",
      "multiple_188",
      "multiple_192",
      "multiple_199"
    ],
    "MISC_ERROR": [
      "multiple_7",
      "multiple_13"
    ],
    "WRONG_VALUE": [
      "multiple_32",
      "multiple_105"
    ],
    "RELEVANT_BUT_INCORRECT": [
      "multiple_33",
      "multiple_47",
      "multiple_58",
      "multiple_61",
      "multiple_91",
      "multiple_99",
      "multiple_186",
      "multiple_193"
    ],
    "EXACTLY_SAME_MEANING": [
      "multiple_25",
      "multiple_29",
      "multiple_79",
      "multiple_89",
      "multiple_94",
      "multiple_151",
      "multiple_172"
    ],
    "LANGUAGE_MISMATCH_RELEVANT_BUT_INCORRECT": [
      "multiple_121",
      "multiple_191"
    ],
    "LANGUAGE_MISMATCH_EXACTLY_SAME_MEANING": [
      "multiple_2",
      "multiple_9",
      "multiple_12",
      "multiple_16",
      "multiple_19",
      "multiple_38",
      "multiple_39",
      "multiple_45",
      "multiple_59",
      "multiple_74",
      "multiple_83",
      "multiple_88",
      "multiple_93",
      "multiple_119",
      "multiple_149",
      "multiple_153",
      "multiple_157",
      "multiple_160",
      "multiple_190"
    ]
  }
}